pastesh/__init__.py
pastesh-0.1.5.dist-info/LICENSE
pastesh-0.1.5.dist-info/METADATA
pastesh-0.1.5.dist-info/WHEEL
pastesh-0.1.5.dist-info/top_level.txt
pastesh-0.1.5.dist-info/RECORD
