Metadata-Version: 2.1
Name: pastesh
Version: 0.1.5
Summary: A Python package for creating encrypted pastes using Paste.sh
Author: Wooyoung Han
Author-email: hanu@a-fin.co.kr
Classifier: Programming Language :: Python :: 3
Classifier: License :: OSI Approved :: MIT License
Classifier: Operating System :: OS Independent
Requires-Python: >=3.6
License-File: LICENSE
Requires-Dist: requests
